encodream
venv
