Metadata-Version: 2.4
Name: encodream
Version: 0.1.0
Summary: Encoding Playground of Dreams - ASCII, UTF-8, machine code visualizer & terminal art tools
Home-page: https://github.com/EdenGithhub/encodream
Author: Eden Simamora
Author-email: Eden Simamora <aeden6877@gmail.com>
License: MIT
Project-URL: Homepage, https://github.com/EdenGithhub/encodream
Project-URL: Source, https://github.com/EdenGithhub/encodream
Project-URL: Issues, https://github.com/EdenGithhub/encodream/issues
Keywords: ascii,utf-8,encoding,visualizer,terminal,pyfiglet,binary,machine code
Requires-Python: >=3.7
License-File: LICENSE
Requires-Dist: numpy
Requires-Dist: matplotlib
Requires-Dist: colorama
Requires-Dist: pyfiglet
Requires-Dist: pandas
Requires-Dist: rich
Requires-Dist: tqdm
Requires-Dist: click
Requires-Dist: tabulate
Requires-Dist: termcolor
Requires-Dist: chardet
Requires-Dist: emoji
Requires-Dist: faker
Requires-Dist: markdownify
Requires-Dist: unidecode
Requires-Dist: humanize
Requires-Dist: pyperclip
Requires-Dist: Pillow
Requires-Dist: validators
Requires-Dist: yaspin
Dynamic: author
Dynamic: home-page
Dynamic: license-file
Dynamic: requires-python
